odoo_sort_manifest_depends/__init__.py
odoo_sort_manifest_depends/__main__.py
odoo_sort_manifest_depends/sort_manifest_deps.py
odoo_sort_manifest_depends-1.4.dist-info/METADATA
odoo_sort_manifest_depends-1.4.dist-info/WHEEL
odoo_sort_manifest_depends-1.4.dist-info/entry_points.txt
odoo_sort_manifest_depends-1.4.dist-info/licenses/LICENSE.txt
odoo_sort_manifest_depends-1.4.dist-info/RECORD
