Metadata-Version: 2.3
Name: odoo-sort-manifest-depends
Version: 1.4
Summary: Sort modules dependencies section in odoo addon's manifest
Project-URL: Documentation, https://github.com/acsone/odoo-sort-manifest-depends#readme
Project-URL: Issues, https://github.com/acsone/odoo-sort-manifest-depends/issues
Project-URL: Source, https://github.com/acsone/odoo-sort-manifest-depends
Author: Acsone
License-Expression: MIT
License-File: LICENSE.txt
Classifier: Development Status :: 4 - Beta
Classifier: Programming Language :: Python
Classifier: Programming Language :: Python :: 3.10
Classifier: Programming Language :: Python :: 3.11
Classifier: Programming Language :: Python :: 3.12
Classifier: Programming Language :: Python :: Implementation :: CPython
Classifier: Programming Language :: Python :: Implementation :: PyPy
Requires-Python: >=3.10
Requires-Dist: click
Requires-Dist: diskcache
Requires-Dist: manifestoo-core>=1.1
Requires-Dist: platformdirs
Requires-Dist: requests
